wink_sdk_user_settings/__init__.py
wink_sdk_user_settings/api_client.py
wink_sdk_user_settings/api_response.py
wink_sdk_user_settings/configuration.py
wink_sdk_user_settings/exceptions.py
wink_sdk_user_settings/py.typed
wink_sdk_user_settings/rest.py
wink_sdk_user_settings/api/__init__.py
wink_sdk_user_settings/api/application_api.py
wink_sdk_user_settings/api/bucket_list_api.py
wink_sdk_user_settings/api/user_settings_api.py
wink_sdk_user_settings/api/webhook_api.py
wink_sdk_user_settings/models/__init__.py
wink_sdk_user_settings/models/address_authenticated_entity.py
wink_sdk_user_settings/models/application.py
wink_sdk_user_settings/models/boolean_response.py
wink_sdk_user_settings/models/bucket_list_entry_authenticated_entity.py
wink_sdk_user_settings/models/bucket_list_entry_request_authenticated_entity.py
wink_sdk_user_settings/models/bucket_list_entry_view_authenticated_entity.py
wink_sdk_user_settings/models/bucket_list_entry_wrapper_authenticated_entity.py
wink_sdk_user_settings/models/change_password_request.py
wink_sdk_user_settings/models/contact_authenticated_entity.py
wink_sdk_user_settings/models/contact_non_authenticated_entity.py
wink_sdk_user_settings/models/country_authenticated_entity.py
wink_sdk_user_settings/models/create_application_response.py
wink_sdk_user_settings/models/custom_monetary_amount.py
wink_sdk_user_settings/models/general_manager_authenticated_entity.py
wink_sdk_user_settings/models/generic_error_message.py
wink_sdk_user_settings/models/geo_json_point_authenticated_entity.py
wink_sdk_user_settings/models/geo_name_authenticated_entity.py
wink_sdk_user_settings/models/hotel_on_map_authenticated_entity.py
wink_sdk_user_settings/models/image_attribution.py
wink_sdk_user_settings/models/image_attribution_authenticated_entity.py
wink_sdk_user_settings/models/inventory_address_authenticated_entity.py
wink_sdk_user_settings/models/inventory_authenticated_entity.py
wink_sdk_user_settings/models/key_value_pair.py
wink_sdk_user_settings-0.0.57.dist-info/licenses/LICENSE
wink_sdk_user_settings-0.0.57.dist-info/METADATA
wink_sdk_user_settings-0.0.57.dist-info/WHEEL
wink_sdk_user_settings-0.0.57.dist-info/top_level.txt
wink_sdk_user_settings-0.0.57.dist-info/RECORD
